supervision/__init__.py
supervision/config.py
supervision/py.typed
supervision/annotators/__init__.py
supervision/annotators/base.py
supervision/annotators/core.py
supervision/annotators/utils.py
supervision/assets/__init__.py
supervision/assets/downloader.py
supervision/assets/list.py
supervision/classification/__init__.py
supervision/classification/core.py
supervision/dataset/__init__.py
supervision/dataset/core.py
supervision/dataset/utils.py
supervision/dataset/formats/__init__.py
supervision/dataset/formats/coco.py
supervision/dataset/formats/pascal_voc.py
supervision/dataset/formats/yolo.py
supervision/detection/__init__.py
supervision/detection/core.py
supervision/detection/line_zone.py
supervision/detection/vlm.py
supervision/detection/tools/__init__.py
supervision/detection/tools/csv_sink.py
supervision/detection/tools/inference_slicer.py
supervision/detection/tools/json_sink.py
supervision/detection/tools/polygon_zone.py
supervision/detection/tools/smoother.py
supervision/detection/tools/transformers.py
supervision/detection/utils/__init__.py
supervision/detection/utils/boxes.py
supervision/detection/utils/converters.py
supervision/detection/utils/internal.py
supervision/detection/utils/iou_and_nms.py
supervision/detection/utils/masks.py
supervision/detection/utils/polygons.py
supervision/draw/__init__.py
supervision/draw/color.py
supervision/draw/utils.py
supervision/geometry/__init__.py
supervision/geometry/core.py
supervision/geometry/utils.py
supervision/keypoint/__init__.py
supervision/keypoint/annotators.py
supervision/keypoint/core.py
supervision/keypoint/skeletons.py
supervision/metrics/__init__.py
supervision/metrics/core.py
supervision/metrics/detection.py
supervision/metrics/f1_score.py
supervision/metrics/mean_average_precision.py
supervision/metrics/mean_average_recall.py
supervision/metrics/precision.py
supervision/metrics/recall.py
supervision/metrics/utils/__init__.py
supervision/metrics/utils/object_size.py
supervision-0.26.0.dist-info/licenses/LICENSE.md
supervision-0.26.0.dist-info/METADATA
supervision-0.26.0.dist-info/WHEEL
supervision-0.26.0.dist-info/top_level.txt
supervision-0.26.0.dist-info/RECORD
