Metadata-Version: 2.4
Name: supervision
Version: 0.26.0
Summary: A set of easy-to-use utils that will come in handy in any Computer Vision project
Author-email: Piotr Skalski <piotr.skalski92@gmail.com>
Maintainer-email: Piotr Skalski <piotr.skalski92@gmail.com>
License: MIT
Project-URL: Homepage, https://github.com/roboflow/supervision
Project-URL: Repository, https://github.com/roboflow/supervision
Project-URL: Documentation, https://supervision.roboflow.com/latest/
Keywords: machine-learning,deep-learning,vision,ML,DL,AI,Roboflow
Classifier: Development Status :: 4 - Beta
Classifier: Intended Audience :: Developers
Classifier: Intended Audience :: Education
Classifier: Intended Audience :: Science/Research
Classifier: License :: OSI Approved :: MIT License
Classifier: Programming Language :: Python :: 3
Classifier: Programming Language :: Python :: 3 :: Only
Classifier: Topic :: Software Development
Classifier: Topic :: Scientific/Engineering
Classifier: Topic :: Scientific/Engineering :: Artificial Intelligence
Classifier: Topic :: Scientific/Engineering :: Image Recognition
Classifier: Typing :: Typed
Classifier: Operating System :: Microsoft :: Windows
Classifier: Operating System :: POSIX :: Linux
Classifier: Operating System :: MacOS
Requires-Python: >=3.9
License-File: LICENSE.md
Requires-Dist: numpy>=1.21.2
Requires-Dist: scipy>=1.10.0
Requires-Dist: matplotlib>=3.6.0
Requires-Dist: pyyaml>=5.3
Requires-Dist: defusedxml>=0.7.1
Requires-Dist: pillow>=9.4
Requires-Dist: requests>=2.26.0
Requires-Dist: tqdm>=4.62.3
Requires-Dist: opencv-python>=4.5.5.64
Provides-Extra: metrics
Requires-Dist: pandas>=2.0.0; extra == "metrics"
Dynamic: license-file
